llamashell/__init__.py
llamashell/llm.py
llamashell/main.py
llamashell/shell.py
llamashell/tools.py
llamashell-0.0.5.dist-info/licenses/LICENSE
llamashell-0.0.5.dist-info/METADATA
llamashell-0.0.5.dist-info/WHEEL
llamashell-0.0.5.dist-info/entry_points.txt
llamashell-0.0.5.dist-info/top_level.txt
llamashell-0.0.5.dist-info/RECORD
